<bankBranchs>
  <bankbranch>
    <name>Samrai</name>
    <city>Samrai</city>
    <address>Near Bus Stand, V. &amp; P.O. Samrai-144032, Distt. Jalandhar</address>
    <contact>01826-275880 </contact>
    <micrCode>NIL </micrCode>
    <ifscCode>CLBL0000002</ifscCode>
    <bankLoc>3716</bankLoc>
  </bankbranch>
  <bankbranch>
    <name>Phagwara</name>
    <city>Phagwara</city>
    <address>14-a, Model Town, G.T. Road, Phagwara - 144401, Distt. Kapurthala</address>
    <contact>01824-500602 </contact>
    <micrCode>144 545 712 </micrCode>
    <ifscCode>CLBL0000003</ifscCode>
    <bankLoc>3717</bankLoc>
  </bankbranch>
  <bankbranch>
    <name>Hoshiarpur</name>
    <city>Hoshiarpur</city>
    <address>204-l, Model Town, Bus Stand Road, Hoshiarpur -146001</address>
    <contact>01882-520314 </contact>
    <micrCode>146 545 002</micrCode>
    <ifscCode>CLBL0000004</ifscCode>
    <bankLoc>3715</bankLoc>
  </bankbranch>
  <bankbranch>
    <name>Mahilpur</name>
    <city>Mahalpur</city>
    <address>Main Road, Near Bus Stand, Mahilpur-146105, Distt. Hoshiarpur</address>
    <contact>01884-500836 </contact>
    <micrCode>NIL </micrCode>
    <ifscCode>CLBL0000005</ifscCode>
    <bankLoc>3715</bankLoc>
  </bankbranch>
  <bankbranch>
    <name>Mehatpur</name>
    <city>Mahatpur</city>
    <address>Main Road, Near Bus Stand, Mehatpur-144041, Distt. Jalandhar</address>
    <contact>01821-250004, </contact>
    <micrCode>NIL </micrCode>
    <ifscCode>CLBL0000006</ifscCode>
    <bankLoc>3716</bankLoc>
  </bankbranch>
  <bankbranch>
    <name>Kapurthala</name>
    <city>Kapurthala</city>
    <address>Jalandhar Road, Near Bus Stand, Kapurthala-144601</address>
    <contact>01822-502829 </contact>
    <micrCode>144 545 102 </micrCode>
    <ifscCode>CLBL0000007</ifscCode>
    <bankLoc>3717</bankLoc>
  </bankbranch>
  <bankbranch>
    <name>Malsian</name>
    <city>Malsian</city>
    <address>Shahkot Road, Near Bus Stand, Malsian - 144701, Distt. Jalandhar</address>
    <contact>01821-502744 </contact>
    <micrCode>NIL </micrCode>
    <ifscCode>CLBL0000008</ifscCode>
    <bankLoc>3716</bankLoc>
  </bankbranch>
  <bankbranch>
    <name>Goraya</name>
    <city>Goraya</city>
    <address>G.T. Road, Goraya-144409, Distt. Jalandhar</address>
    <contact>01826-501893 </contact>
    <micrCode>144 545 302</micrCode>
    <ifscCode>CLBL0000009</ifscCode>
    <bankLoc>3716</bankLoc>
  </bankbranch>
  <bankbranch>
    <name>Nurmahal</name>
    <city>Nurmahal</city>
    <address>Main Road, Nurmahal - 144039, Distt. Jalandhar</address>
    <contact>01826-503307 </contact>
    <micrCode>144 545 602</micrCode>
    <ifscCode>CLBL0000010</ifscCode>
    <bankLoc>3716</bankLoc>
  </bankbranch>
  <bankbranch>
    <name>Shankar</name>
    <city>Shanker</city>
    <address>Near Bus Stand, V. &amp; P.O. Shankar - 144042, Tehsil Nakodar, Distt. Jalandhar</address>
    <contact>01821-246489 </contact>
    <micrCode>NIL </micrCode>
    <ifscCode>CLBL0000011</ifscCode>
    <bankLoc>3716</bankLoc>
  </bankbranch>
  <bankbranch>
    <name>Rurki</name>
    <city>Rourka Kalan</city>
    <address>Main Chowk, V. &amp; P.O. Rurki-141305, Tehsil Phillaur, Distt. Jalandhar</address>
    <contact>01826-276363 </contact>
    <micrCode>NIL </micrCode>
    <ifscCode>CLBL0000012</ifscCode>
    <bankLoc>3716</bankLoc>
  </bankbranch>
  <bankbranch>
    <name>Jalandhar</name>
    <city>Jalandhar</city>
    <address>36, G.T. Road, Jalandhar-144001</address>
    <contact>0181-5050603 </contact>
    <micrCode>144 545 002</micrCode>
    <ifscCode>CLBL0000013</ifscCode>
    <bankLoc>3716</bankLoc>
  </bankbranch>
  <bankbranch>
    <name>Bhogpur</name>
    <city>Bhogpur</city>
    <address>G.T. Road, Bhogpur -144201, Distt. Jalandhar</address>
    <contact>0181-5060280 </contact>
    <micrCode>144 545 977 </micrCode>
    <ifscCode>CLBL0000014</ifscCode>
    <bankLoc>3716</bankLoc>
  </bankbranch>
  <bankbranch>
    <name>Lohian</name>
    <city>Lohian Khas</city>
    <address>Main Road, Lohian-144629, Tehsil Shahkot, Distt. Jalandhar</address>
    <contact>01821-501584 </contact>
    <micrCode>NIL </micrCode>
    <ifscCode>CLBL0000015</ifscCode>
    <bankLoc>3716</bankLoc>
  </bankbranch>
  <bankbranch>
    <name>Begowal</name>
    <city>Begowal</city>
    <address>Main Road, Opp. Bus Stand, V.&amp; P.O. Begowal-144621, Tehsil Bholath, Distt. Kapurthala</address>
    <contact>01822-502370 </contact>
    <micrCode>144 545 987 </micrCode>
    <ifscCode>CLBL0000016</ifscCode>
    <bankLoc>3717</bankLoc>
  </bankbranch>
  <bankbranch>
    <name>Jandiala</name>
    <city>Jundiala</city>
    <address>Near Bus Stand, Jalandhar Road, V. &amp;p.O. Jandiala - 144031, Tehsil Phillaur, Distt. Jalandhar</address>
    <contact>01826-274004 </contact>
    <micrCode>NIL </micrCode>
    <ifscCode>CLBL0000017</ifscCode>
    <bankLoc>3716</bankLoc>
  </bankbranch>
  <bankbranch>
    <name>Shahkot</name>
    <city>Shahkot</city>
    <address>Moga Road, Near Grain Market, Shahkot-144702, Distt. Jalandhar</address>
    <contact>01821-503457 </contact>
    <micrCode>144 545 902 </micrCode>
    <ifscCode>CLBL0000018</ifscCode>
    <bankLoc>3716</bankLoc>
  </bankbranch>
  <bankbranch>
    <name>Sultanpur Lodhi</name>
    <city>Sultanpur Lodhi</city>
    <address>Near Shaheed Udham Singh Chowk, Kapurthala Road, Sultanpur Lodhi - 144626, Distt. Kapurthala</address>
    <contact>01828-502000 </contact>
    <micrCode>144 545 612 </micrCode>
    <ifscCode>CLBL0000019</ifscCode>
    <bankLoc>3717</bankLoc>
  </bankbranch>
  <bankbranch>
    <name>Bilga</name>
    <city>Bilga</city>
    <address>Near Patti Nelowal Chowk, V.&amp;p.O. Bilga-144036, Tehsil Phillaur, Distt. Jalandhar</address>
    <contact>01826-245062 </contact>
    <micrCode>NIL </micrCode>
    <ifscCode>CLBL0000020</ifscCode>
    <bankLoc>3716</bankLoc>
  </bankbranch>
  <bankbranch>
    <name>Mukerian</name>
    <city>Mukerian</city>
    <address>Near Bus Stand, Mukerian - 144211, Distt. Hoshiarpur</address>
    <contact>01883-502700 </contact>
    <micrCode>144 545 212 </micrCode>
    <ifscCode>CLBL0000021</ifscCode>
    <bankLoc>3715</bankLoc>
  </bankbranch>
  <bankbranch>
    <name>Tanda</name>
    <city>Urmar Tanda</city>
    <address>Near Jaja Chowk, Sri Hargobindpur Road, Tanda-144203, Distt. Hoshiarpur</address>
    <contact>01886-227280 </contact>
    <micrCode>144 545 312</micrCode>
    <ifscCode>CLBL0000022</ifscCode>
    <bankLoc>3715</bankLoc>
  </bankbranch>
  <bankbranch>
    <name>Kala Sanghian</name>
    <city>Kala Sangian</city>
    <address>Jalandhar Road, V. &amp; P.O. Kala Sanghian - 144623, Distt. Kapurthala</address>
    <contact>01822-258084 </contact>
    <micrCode>NIL </micrCode>
    <ifscCode>CLBL0000023</ifscCode>
    <bankLoc>3717</bankLoc>
  </bankbranch>
  <bankbranch>
    <name>Rurka Kalan</name>
    <city>Rourka Kalan</city>
    <address>Near Bus Stand, Goraya Road, V.P.O. Rurka Kalan-144031, Tehsil Phillaur, Distt. Jalandhar</address>
    <contact>01826-276222 </contact>
    <micrCode>NIL </micrCode>
    <ifscCode>CLBL0000024</ifscCode>
    <bankLoc>3716</bankLoc>
  </bankbranch>
  <bankbranch>
    <name>Jalandhr</name>
    <city>Jalandhar</city>
    <address>143, Vijay Nagar, Nr. Football Chowk, Mahavir Marg, Jalandhar</address>
    <contact>0181-5026666 </contact>
    <micrCode>144 545 003</micrCode>
    <ifscCode>CLBL0000025</ifscCode>
    <bankLoc>3716</bankLoc>
  </bankbranch>
  <bankbranch>
    <name>Nakodar</name>
    <city>Nakodar</city>
    <address>Nurmahal Road, Nakodar-144040, Distt. Jalandhar</address>
    <contact>01821-502101 </contact>
    <micrCode>144 545 202</micrCode>
    <ifscCode>CLBL0000999</ifscCode>
    <bankLoc>3716</bankLoc>
  </bankbranch>
  <bankbranch>
    <name>Head Office, Jalandhar</name>
    <city>Jalandhar</city>
    <address>Midas Corporate Park, 3rd Floor, 37, G.T. Road, Jalandhar</address>
    <contact>0181-5052222 </contact>
    <micrCode></micrCode>
    <ifscCode>CLBL0000001</ifscCode>
    <bankLoc>3716</bankLoc>
  </bankbranch>
  <bankbranch>
    <name>Phillaur</name>
    <city>Phillaur</city>
    <address>Prithvi Tower’, Near Bus Stand, G.T. Road, Phillaur--144410, Distt. Jalandhar</address>
    <contact>0182-6500444 </contact>
    <micrCode>144 545 502</micrCode>
    <ifscCode>CLBL0000026</ifscCode>
    <bankLoc>3716</bankLoc>
  </bankbranch>
  <bankbranch>
    <name>Adampur</name>
    <city>Adampur</city>
    <address>Main Road, Adampur-144103, Distt. Jalandhar</address>
    <contact>0181-5090777 </contact>
    <micrCode>144 545 552</micrCode>
    <ifscCode>CLBL0000027</ifscCode>
    <bankLoc>3716</bankLoc>
  </bankbranch>
  <bankbranch>
    <name>Chabbewal</name>
    <city>Chabbewal</city>
    <address>Hoshiarpur Road, Adda Chabbewal 146102, Distt. Hoshiarpur</address>
    <contact>0188-2270250 </contact>
    <micrCode>146 545 003</micrCode>
    <ifscCode>CLBL0000028</ifscCode>
    <bankLoc>3715</bankLoc>
  </bankbranch>
  <bankbranch>
    <name>Dasuya</name>
    <city>Dasuya</city>
    <address>G.T. Road, Near Lic Building, Dasuya – 144205, Distt. Hoshiarpur</address>
    <contact>0188-3500333 </contact>
    <micrCode>144 545 877</micrCode>
    <ifscCode>CLBL0000029</ifscCode>
    <bankLoc>3715</bankLoc>
  </bankbranch>
  <bankbranch>
    <name>Ludhiana</name>
    <city>Ludhiana</city>
    <address>Bxx-3360, Gurdev Nagar, (near Aarti Cinema), Ludhiana-141001</address>
    <contact>0161-5014444 </contact>
    <micrCode>141 545 002</micrCode>
    <ifscCode>CLBL0000030</ifscCode>
    <bankLoc>3718</bankLoc>
  </bankbranch>
  <bankbranch>
    <name>Amritsar</name>
    <city>Amritsar</city>
    <address>Central Mall’, 32, Mall Road, Amritsar – 143001|</address>
    <contact>Tel. : 0183-5093333, 5053333; 5255505 </contact>
    <micrCode>143545002</micrCode>
    <ifscCode>CLBL0000031</ifscCode>
    <bankLoc>3714</bankLoc>
  </bankbranch>
  <bankbranch>
    <name>Jamsher</name>
    <city>Jamsher</city>
    <address>Jalandhar Cantt Road, V. &amp; P.O. Jamsher - 144020</address>
    <contact>2775111 </contact>
    <micrCode>144545004</micrCode>
    <ifscCode>CLBL0000032</ifscCode>
    <bankLoc>3716</bankLoc>
  </bankbranch>
  <bankbranch>
    <name>Kartarpur</name>
    <city>Kartarpur</city>
    <address>G.T. Road, Kartarpur-144801</address>
    <contact>5050759 </contact>
    <micrCode>144 545 802 </micrCode>
    <ifscCode>CLBL0000033</ifscCode>
    <bankLoc>3716</bankLoc>
  </bankbranch>
  <bankbranch>
    <name>Dakha</name>
    <city>Dakha</city>
    <address>Ferozepur Road, V. &amp; P.O. Dakha - 141101</address>
    <contact>5050759 </contact>
    <micrCode>141 545 003</micrCode>
    <ifscCode>CLBL0000034</ifscCode>
    <bankLoc>3718</bankLoc>
  </bankbranch>
</bankBranchs>