<bankBranchs>
  <bankbranch>
    <name>Andheri Branch</name>
    <city>Mumbai</city>
    <address>Andheri Branch, 5&amp; 6, Vruj Vihar CO. OP. HOU. SOC. Ltd, Pali RAM Road, Andheri (W), MUMBAI.</address>
    <contact>26205703</contact>
    <micrCode>400128002</micrCode>
    <ifscCode>NNSB0128051</ifscCode>
    <bankLoc>13462</bankLoc>
  </bankbranch>
  <bankbranch>
    <name>Ring Road</name>
    <city>Surat</city>
    <address>Shop NO.1004, 1005, 1006, Krishna Textile Market, Near JJ Textile Market, Umarwada, Ring Road, SURAT-395002.</address>
    <contact>2147483647</contact>
    <micrCode>395128002</micrCode>
    <ifscCode>NNSB0128041</ifscCode>
    <bankLoc>13461</bankLoc>
  </bankbranch>
  <bankbranch>
    <name>Bopal</name>
    <city>Ahmedabad</city>
    <address>Shop NO. 15, 16, Orchid Center, OPP. Safal Parisar, South Bopal, Ahmedabad - 380058</address>
    <contact>298410</contact>
    <micrCode>380128022</micrCode>
    <ifscCode>NNSB0128022</ifscCode>
    <bankLoc>13460</bankLoc>
  </bankbranch>
  <bankbranch>
    <name>Odhav</name>
    <city>Ahmedabad</city>
    <address>B-7, Barsilona Multiple Business Compus, NR.ODHAV Ringroad Circle, Odhav Ring Road, Odhav, Ahmedabad-382415</address>
    <contact>2147483647</contact>
    <micrCode>380128011</micrCode>
    <ifscCode>NNSB0128021</ifscCode>
    <bankLoc>13460</bankLoc>
  </bankbranch>
  <bankbranch>
    <name>Changodar Branch</name>
    <city>Ahmedabad</city>
    <address>Changodar Branch, 12-13, Kailash Avenue, Ashwamegh Asset, OPP. M.N.DESAI Petrol Pump, Sarkhej-bavla Highway, Changodar, Ahmedabad - 382210</address>
    <contact>2147483647</contact>
    <micrCode>328128020</micrCode>
    <ifscCode>NNSB0128020</ifscCode>
    <bankLoc>13460</bankLoc>
  </bankbranch>
  <bankbranch>
    <name>Maninagar Branch</name>
    <city>Ahmedabad</city>
    <address>Maninagar Branch, Shop NO. 1 TO 4, 1ST Floor, Swastik Plaza, Near Vallabh Wadi, Bhairavnath Road, Maninagar, Ahmedabad - 380 008</address>
    <contact>25466650</contact>
    <micrCode>328128019</micrCode>
    <ifscCode>NNSB0128019</ifscCode>
    <bankLoc>13460</bankLoc>
  </bankbranch>
  <bankbranch>
    <name>Thaltej Branch</name>
    <city>Ahmedabad</city>
    <address>Thaltej Branch, 1 &amp; 16, Gopi Complex, I Floor, OPP.HOME Town, Thaltej, Ahmedabad - 380 054.</address>
    <contact>26852219</contact>
    <micrCode>328128018</micrCode>
    <ifscCode>NNSB0128018</ifscCode>
    <bankLoc>13460</bankLoc>
  </bankbranch>
  <bankbranch>
    <name>Vejalpur Branch</name>
    <city>Ahmedabad</city>
    <address>Vejalpur Branch, 4,ground Floor, Regency Plaza, OPP.RAHUL Tower, NR.100&apos;FT Road, Vejalpur, Ahmedabad - 380 015.</address>
    <contact>26931821</contact>
    <micrCode>328128017</micrCode>
    <ifscCode>NNSB0128017</ifscCode>
    <bankLoc>13460</bankLoc>
  </bankbranch>
  <bankbranch>
    <name>Sharda Mandir Branch</name>
    <city>Ahmedabad</city>
    <address>NEW S. M. Road Branch, 49, Vasant Kunj Society, NEW S.M. Road, Paldi, Ahmedabad - 380 007.</address>
    <contact>26607399</contact>
    <micrCode>328128016</micrCode>
    <ifscCode>NNSB0128016</ifscCode>
    <bankLoc>13460</bankLoc>
  </bankbranch>
  <bankbranch>
    <name>Narayan Nagar Branch</name>
    <city>Ahmedabad</city>
    <address>Narayan Nagar Branch, 6,rakesh Society, NR.SHANTIVAN, Paldi, Ahmedabad - 380 007.</address>
    <contact>26670226</contact>
    <micrCode>328128015</micrCode>
    <ifscCode>NNSB0128015</ifscCode>
    <bankLoc>13460</bankLoc>
  </bankbranch>
  <bankbranch>
    <name>Naranpura Branch</name>
    <city>Ahmedabad</city>
    <address>Naranpura Branch, Vijaynagar, Pragati Nagar Road, Naranpura, Ahmedabad - 380 013.</address>
    <contact>27431043</contact>
    <micrCode>328128014</micrCode>
    <ifscCode>NNSB0128014</ifscCode>
    <bankLoc>13460</bankLoc>
  </bankbranch>
  <bankbranch>
    <name>Isanpur Branch</name>
    <city>Ahmedabad</city>
    <address>Isanpur Branch, OPP.SNEHKUNJ Society, NR.ISANPUR Bus-stop, Isanpur, Ahmedabad - 382 443.</address>
    <contact>25734414</contact>
    <micrCode>328128013</micrCode>
    <ifscCode>NNSB0128013</ifscCode>
    <bankLoc>13460</bankLoc>
  </bankbranch>
  <bankbranch>
    <name>LAW Garden Branch</name>
    <city>Ahmedabad</city>
    <address>LAW Garden Branch, OPP.SAMARTHESHWAR Mahadev, NR.LAW Garden, Ellisbridge, Ahmedabad - 380 006.</address>
    <contact>26443724</contact>
    <micrCode>328128012</micrCode>
    <ifscCode>NNSB0128012</ifscCode>
    <bankLoc>13460</bankLoc>
  </bankbranch>
  <bankbranch>
    <name>Satellite Branch</name>
    <city>Ahmedabad</city>
    <address>Jodhpur-satellite Branch, 129, Vrundavan, 132&apos;ft Ring Road, Satellite, Ahmedabad- 380 015.</address>
    <contact>26779694</contact>
    <micrCode>328128011</micrCode>
    <ifscCode>NNSB0128011</ifscCode>
    <bankLoc>13460</bankLoc>
  </bankbranch>
  <bankbranch>
    <name>Panjara Pole Branch</name>
    <city>Ahmedabad</city>
    <address>Panjarapole Branch, 17-18, Kamdhenu Complex, OPP.SAHAJANAND College, Panjarapole, Ahmedabad - 380 015.</address>
    <contact>26302109</contact>
    <micrCode>328128010</micrCode>
    <ifscCode>NNSB0128010</ifscCode>
    <bankLoc>13460</bankLoc>
  </bankbranch>
  <bankbranch>
    <name>Drive IN Branch</name>
    <city>Ahmedabad</city>
    <address>Drive-in Road Branch, 188/871, Minesota Appartment, NR.VIJAY Char Rasta, Drive-in Road, Ahmedabad-380 009.</address>
    <contact>27912761</contact>
    <micrCode>328128009</micrCode>
    <ifscCode>NNSB0128009</ifscCode>
    <bankLoc>13460</bankLoc>
  </bankbranch>
  <bankbranch>
    <name>Vasna Branch</name>
    <city>Ahmedabad</city>
    <address>Vasna Branch, Ground Floor, Jindarshan Building, OPP.VASNA Bus-stop, Vasna, AHMEDABAD-380007.</address>
    <contact>26605486</contact>
    <micrCode>328128008</micrCode>
    <ifscCode>NNSB0128008</ifscCode>
    <bankLoc>13460</bankLoc>
  </bankbranch>
  <bankbranch>
    <name>Bapunagar Branch</name>
    <city>Ahmedabad</city>
    <address>Bapunagar Branch, 11, Sukhsagar Complex, OPP.DINESH Chambers, NR.SAYONA Arcade, Bapunagar, Ahmedabad - 380 024.</address>
    <contact>22200084</contact>
    <micrCode>328128007</micrCode>
    <ifscCode>NNSB0128007</ifscCode>
    <bankLoc>13460</bankLoc>
  </bankbranch>
  <bankbranch>
    <name>Rakhial Branch</name>
    <city>Ahmedabad</city>
    <address>Rakhial Branch, Vora Chamber, OPP.MUNI Pumping Station, Rakhial, Ahmedabad- 23.</address>
    <contact>22748642</contact>
    <micrCode>328128006</micrCode>
    <ifscCode>NNSB0128006</ifscCode>
    <bankLoc>13460</bankLoc>
  </bankbranch>
  <bankbranch>
    <name>Ashram Road Branch</name>
    <city>Ahmedabad</city>
    <address>Ashram Road Branch, Shilp-ii, NR.PETROL Pump, NR.INCOME TAX Office, Ashram Road, Ahmedabad - 380 009.</address>
    <contact>27541031</contact>
    <micrCode>328128005</micrCode>
    <ifscCode>NNSB0128005</ifscCode>
    <bankLoc>13460</bankLoc>
  </bankbranch>
  <bankbranch>
    <name>Shanti COMM. Branch</name>
    <city>Ahmedabad</city>
    <address>Shanti COMM. Centre Branch, 36, Shanti COMM.CENTRE, Nagar Sheth NO Vando, Gheekanta, Ahmedabad- 380001</address>
    <contact>25508914</contact>
    <micrCode>328128004</micrCode>
    <ifscCode>NNSB0128004</ifscCode>
    <bankLoc>13460</bankLoc>
  </bankbranch>
  <bankbranch>
    <name>Newcloth Branch</name>
    <city>Ahmedabad</city>
    <address>NEW Cloth Market Branch, NEW Cloth Market, O/S.RAIPUR Gate, Ahmedabad-1</address>
    <contact>22114136</contact>
    <micrCode>328128003</micrCode>
    <ifscCode>NNSB0128003</ifscCode>
    <bankLoc>13460</bankLoc>
  </bankbranch>
  <bankbranch>
    <name>Maskati Branch</name>
    <city>Ahmedabad</city>
    <address>Maskati Market Branch, Manilal Mansion, Relief Road, Ahmedabad-1</address>
    <contact>22138015</contact>
    <micrCode>328128002</micrCode>
    <ifscCode>NNSB0128002</ifscCode>
    <bankLoc>13460</bankLoc>
  </bankbranch>
</bankBranchs>