<bankBranchs>
  <bankbranch>
    <name>Pondicherry State Cooperative Bank LTD.</name>
    <city>Puducherry</city>
    <address>204, East Coast Road, Olandaikeerapalayam, Mudaliarpet Post, Puducherry - 605 004</address>
    <contact>2285303</contact>
    <micrCode>NA</micrCode>
    <ifscCode>TNSC0160101</ifscCode>
    <bankLoc>22738</bankLoc>
  </bankbranch>
  <bankbranch>
    <name>Neft Routing</name>
    <city>Chennai</city>
    <address>233 NSC Bose Road Georgetown -600001</address>
    <contact>25340973</contact>
    <micrCode>NA</micrCode>
    <ifscCode>TNSC00ROUTE</ifscCode>
    <bankLoc>22739</bankLoc>
  </bankbranch>
  <bankbranch>
    <name>THE Tamilnadu Industrial Co-operative Bank LTD</name>
    <city>Chennai</city>
    <address>36, South Canal Bank Road Rajaannamalaipuram Mandavelipakkam Chennai - 600028</address>
    <contact>24951509</contact>
    <micrCode>NA</micrCode>
    <ifscCode>TNSC0015000</ifscCode>
    <bankLoc>22739</bankLoc>
  </bankbranch>
  <bankbranch>
    <name>THE Villupuram District Central Cooperative Bank LTD.</name>
    <city>Villupuram</city>
    <address>2,hospital Road, Villupuram-605 602</address>
    <contact>224803</contact>
    <micrCode>NA</micrCode>
    <ifscCode>TNSC0012200</ifscCode>
    <bankLoc>22759</bankLoc>
  </bankbranch>
  <bankbranch>
    <name>THE Thoothukudi District Central Cooperative Bank LTD.</name>
    <city>Thoothukudi</city>
    <address>109/5d, Ettayapuram Road, Polepettai, Thoothukudi-628002</address>
    <contact>2347604</contact>
    <micrCode>NA</micrCode>
    <ifscCode>TNSC0012100</ifscCode>
    <bankLoc>22754</bankLoc>
  </bankbranch>
  <bankbranch>
    <name>THE Tiruvannamalai District Central Cooperative Bank LTD.</name>
    <city>Tiruvannamalai</city>
    <address>9,6th Street, Gandhi Nagar, Tiruvannamalai - 606 601</address>
    <contact>224331</contact>
    <micrCode>NA</micrCode>
    <ifscCode>TNSC0012000</ifscCode>
    <bankLoc>22757</bankLoc>
  </bankbranch>
  <bankbranch>
    <name>THE Sivagangai District Central Cooperative Bank LTD.</name>
    <city>Sivagangai</city>
    <address>163, Gandhi Street, Sivagangai - 630 561</address>
    <contact>240645</contact>
    <micrCode>NA</micrCode>
    <ifscCode>TNSC0011900</ifscCode>
    <bankLoc>22752</bankLoc>
  </bankbranch>
  <bankbranch>
    <name>THE Virudhunagar District Central Cooperative Bank LTD.</name>
    <city>Virudhunagar</city>
    <address>104/1, Madurai Road, Virudhunagar - 626 001</address>
    <contact>245815</contact>
    <micrCode>NA</micrCode>
    <ifscCode>TNSC0011800</ifscCode>
    <bankLoc>22760</bankLoc>
  </bankbranch>
  <bankbranch>
    <name>THE Dindigul Central Cooperative Bank LTD</name>
    <city>Dindigul</city>
    <address>COOP.NAGAR, Tiruchi Road, Dindigul - 624 005</address>
    <contact>2433153</contact>
    <micrCode>NA</micrCode>
    <ifscCode>TNSC0011700</ifscCode>
    <bankLoc>22743</bankLoc>
  </bankbranch>
  <bankbranch>
    <name>THE Vellore District Central Cooperative Bank Limited</name>
    <city>Vellore</city>
    <address>NO.3, Officers Line, Vellore - 632 001</address>
    <contact>2220522</contact>
    <micrCode>NA</micrCode>
    <ifscCode>TNSC0011600</ifscCode>
    <bankLoc>22758</bankLoc>
  </bankbranch>
  <bankbranch>
    <name>THE Tirunelveli District Central Cooperative Bank LTD.</name>
    <city>Tirunelveli</city>
    <address>Trivandrum Road, Vannarpet, Tirunelveli - 627003</address>
    <contact>2500281</contact>
    <micrCode>NA</micrCode>
    <ifscCode>TNSC0011500</ifscCode>
    <bankLoc>22756</bankLoc>
  </bankbranch>
  <bankbranch>
    <name>THE Tiruchirapalli District Central Cooperative Bank LTD.</name>
    <city>Tiruchirapalli</city>
    <address>NO.1, Fort Station Road, Teppakulam, Tiruchirapalli-620002</address>
    <contact>2702441</contact>
    <micrCode>NA</micrCode>
    <ifscCode>TNSC0011400</ifscCode>
    <bankLoc>22755</bankLoc>
  </bankbranch>
  <bankbranch>
    <name>THE Thanjavur Central Cooperative Bank LTD.</name>
    <city>Thanjavur</city>
    <address>331, Mela Veethi, Thanjavur - 613 009</address>
    <contact>223322</contact>
    <micrCode>NA</micrCode>
    <ifscCode>TNSC0011300</ifscCode>
    <bankLoc>22753</bankLoc>
  </bankbranch>
  <bankbranch>
    <name>THE Cuddalore District Central Cooperative Bank LTD.</name>
    <city>Cuddalore</city>
    <address>Beach Road, Cuddalore - 607 001</address>
    <contact>295911</contact>
    <micrCode>NA</micrCode>
    <ifscCode>TNSC0011200</ifscCode>
    <bankLoc>22741</bankLoc>
  </bankbranch>
  <bankbranch>
    <name>THE Salem District Central Cooperative Bank LTD.</name>
    <city>Salem</city>
    <address>153/65-a, Cherry Road, Salem - 636 001</address>
    <contact>2451761</contact>
    <micrCode>NA</micrCode>
    <ifscCode>TNSC0011100</ifscCode>
    <bankLoc>22751</bankLoc>
  </bankbranch>
  <bankbranch>
    <name>THE Ramanathapuram District Central Cooperative Bank LTD.</name>
    <city>Ramanathapuram</city>
    <address>265-e, Vandikara Street, Ramanathapuram-623 501</address>
    <contact>220149</contact>
    <micrCode>NA</micrCode>
    <ifscCode>TNSC0011000</ifscCode>
    <bankLoc>22750</bankLoc>
  </bankbranch>
  <bankbranch>
    <name>THE Pudukkottai District Central Cooperative Bank LTD.</name>
    <city>Pudukkottai</city>
    <address>834-836, East Main Street, Pudukkottai-622 001</address>
    <contact>222389</contact>
    <micrCode>NA</micrCode>
    <ifscCode>TNSC0010900</ifscCode>
    <bankLoc>22749</bankLoc>
  </bankbranch>
  <bankbranch>
    <name>THE Erode District Central Cooperative Bank LTD.</name>
    <city>Erode</city>
    <address>Bhavani Main Road, Erode - 638 003</address>
    <contact>2213401</contact>
    <micrCode>NA</micrCode>
    <ifscCode>TNSC0010800</ifscCode>
    <bankLoc>22744</bankLoc>
  </bankbranch>
  <bankbranch>
    <name>THE Nilgiris District Central Cooperative Bank LTD.</name>
    <city>Udhagamandalam</city>
    <address>Charring Cross, Udhagamandalam-643 001</address>
    <contact>2443978</contact>
    <micrCode>NA</micrCode>
    <ifscCode>TNSC0010700</ifscCode>
    <bankLoc>22748</bankLoc>
  </bankbranch>
  <bankbranch>
    <name>THE Madurai District Central Cooperative Bank LTD.</name>
    <city>Madurai</city>
    <address>187, North Veli Street, Madurai - 625 001</address>
    <contact>2342051</contact>
    <micrCode>NA</micrCode>
    <ifscCode>TNSC0010600</ifscCode>
    <bankLoc>22747</bankLoc>
  </bankbranch>
  <bankbranch>
    <name>THE Chennai Central Cooperative Bank LTD.</name>
    <city>Chennai</city>
    <address>215, Prakasam Salai, Chennai - 600 108</address>
    <contact>23458708</contact>
    <micrCode>NA</micrCode>
    <ifscCode>TNSC0010500</ifscCode>
    <bankLoc>22739</bankLoc>
  </bankbranch>
  <bankbranch>
    <name>THE Kumbakonam Central Cooperative Bank LTD.</name>
    <city>Kumbakonam</city>
    <address>2,T.S.R.BIG Street, Kumbakonam-612 001</address>
    <contact>2430073</contact>
    <micrCode>NA</micrCode>
    <ifscCode>TNSC0010400</ifscCode>
    <bankLoc>22753</bankLoc>
  </bankbranch>
  <bankbranch>
    <name>THE Kanyakumari District Central Cooperative Bank LTD.</name>
    <city>Nagercoil</city>
    <address>Alexander Press Road, Nagercoil-629001</address>
    <contact>233384</contact>
    <micrCode>NA</micrCode>
    <ifscCode>TNSC0010300</ifscCode>
    <bankLoc>22746</bankLoc>
  </bankbranch>
  <bankbranch>
    <name>THE Kanchipuram Central Cooperative Bank LTD.</name>
    <city>Kanchipuram</city>
    <address>15-g, Sheikpet North Street, Kanchipuram-631 501</address>
    <contact>27222296</contact>
    <micrCode>NA</micrCode>
    <ifscCode>TNSC0010200</ifscCode>
    <bankLoc>22745</bankLoc>
  </bankbranch>
  <bankbranch>
    <name>THE Dharmapuri District Central Cooperative Bank LTD.</name>
    <city>Dharmapuri</city>
    <address>81/10h, Nethaji Bye-pass Road, Dharmapuri-636 701</address>
    <contact>260051</contact>
    <micrCode>NA</micrCode>
    <ifscCode>TNSC0010100</ifscCode>
    <bankLoc>22742</bankLoc>
  </bankbranch>
  <bankbranch>
    <name>THE Coimbatore District Central Cooperative Bank LTD.</name>
    <city>Coimbatore</city>
    <address>80, Bank Road, Coimbatore - 641018</address>
    <contact>2302447</contact>
    <micrCode>NA</micrCode>
    <ifscCode>TNSC0010000</ifscCode>
    <bankLoc>22740</bankLoc>
  </bankbranch>
  <bankbranch>
    <name>Headoffice</name>
    <city>Chennai</city>
    <address>233, N.S.C Bose Road Chennai 600001</address>
    <contact>25340973</contact>
    <micrCode>600091001</micrCode>
    <ifscCode>TNSC0000001</ifscCode>
    <bankLoc>22739</bankLoc>
  </bankbranch>
</bankBranchs>